roblox_version/__init__.py
roblox_version/version.py
roblox_version-1.0.1.dist-info/LICENSE
roblox_version-1.0.1.dist-info/METADATA
roblox_version-1.0.1.dist-info/WHEEL
roblox_version-1.0.1.dist-info/top_level.txt
roblox_version-1.0.1.dist-info/RECORD
