Metadata-Version: 2.1
Name: roblox_version
Version: 1.0.1
License-File: LICENSE
Requires-Dist: asyncio
Requires-Dist: httpx
